snowplot/__init__.py
snowplot/cli.py
snowplot/config.ini
snowplot/master.ini
snowplot/plotting.py
snowplot/profiles.py
snowplot/recipes.ini
snowplot/snowplot.py
snowplot/utilities.py
snowplot-0.2.0.dist-info/AUTHORS.rst
snowplot-0.2.0.dist-info/LICENSE
snowplot-0.2.0.dist-info/METADATA
snowplot-0.2.0.dist-info/WHEEL
snowplot-0.2.0.dist-info/entry_points.txt
snowplot-0.2.0.dist-info/top_level.txt
snowplot-0.2.0.dist-info/RECORD
