Metadata-Version: 2.1
Name: snowplot
Version: 0.2.0
Summary: A python package for plotting vertical profiles for analyzing snow
Home-page: https://github.com/micahjohnson150/snowplot
Author: Micah Johnson
Author-email: micah.johnson150@gmail.com
License: BSD license
Keywords: snowplot
Platform: UNKNOWN
Classifier: Development Status :: 2 - Pre-Alpha
Classifier: Intended Audience :: Developers
Classifier: License :: OSI Approved :: BSD License
Classifier: Natural Language :: English
Classifier: Programming Language :: Python :: 3.6
Classifier: Programming Language :: Python :: 3.7
Classifier: Programming Language :: Python :: 3.8
Requires-Python: >=3.5
